Metadata-Version: 1.1
Name: shrincols
Version: 0.1.1
Summary: Tool for fit string to a fixed number of cols.
Home-page: https://github.com/thiagolcmelo/shrincols
Author: Thiago Melo
Author-email: thiago.lc.melo@gmail.com
License: UNKNOWN
Download-URL: https://github.com/thiagolcmelo/shrincols/archive/0.1.1.tar.gz
Platform: UNKNOWN
